paramagpy/__init__.py
paramagpy/_version.py
paramagpy/dataparse.py
paramagpy/fit.py
paramagpy/gui.py
paramagpy/icon.gif
paramagpy/metal.py
paramagpy/protein.py
paramagpy-1.2.dist-info/LICENSE
paramagpy-1.2.dist-info/METADATA
paramagpy-1.2.dist-info/WHEEL
paramagpy-1.2.dist-info/top_level.txt
paramagpy-1.2.dist-info/RECORD
