Metadata-Version: 2.1
Name: paramagpy
Version: 1.2
Summary: Calculate paramagnetic effects in NMR spectra of proteins
Home-page: https://github.com/henryorton/paramagpy
Author: Henry Orton
Author-email: henry.orton@anu.edu.au
License: GNU GPLv3+
Platform: UNKNOWN
Classifier: Programming Language :: Python :: 3
Classifier: License :: OSI Approved :: GNU General Public License v3 or later (GPLv3+)
Classifier: Operating System :: OS Independent
License-File: LICENSE
Requires-Dist: numpy
Requires-Dist: scipy
Requires-Dist: matplotlib
Requires-Dist: biopython
